acceptable/__init__.py
acceptable/__main__.py
acceptable/_build_doubles.py
acceptable/_doubles.py
acceptable/_service.py
acceptable/_validation.py
acceptable/djangoutil.py
acceptable/dummy_importer.py
acceptable/generate_doubles.py
acceptable/generate_mocks.py
acceptable/lint.py
acceptable/mocks.py
acceptable/openapi.py
acceptable/responses.py
acceptable/util.py
acceptable/make/Makefile.acceptable
acceptable/management/__init__.py
acceptable/management/commands/__init__.py
acceptable/management/commands/acceptable.py
acceptable/templates/api_group.md.j2
acceptable/templates/index.md.j2
acceptable-0.39.dist-info/LICENSE
acceptable-0.39.dist-info/METADATA
acceptable-0.39.dist-info/WHEEL
acceptable-0.39.dist-info/entry_points.txt
acceptable-0.39.dist-info/top_level.txt
acceptable-0.39.dist-info/RECORD
