Metadata-Version: 2.1
Name: acceptable
Version: 0.39
Summary: API metadata and schema tool for generating tests and documentation
Home-page: https://github.com/canonical/acceptable
Author: Canonical Online Services
Author-email: online-services@lists.canonical.com
License: LGPLv3
License-File: LICENSE
Requires-Dist: jsonschema
Requires-Dist: pyyaml
Requires-Dist: Jinja2
Provides-Extra: django
Requires-Dist: django (<3,>=2.1) ; extra == 'django'
Provides-Extra: flask
Requires-Dist: Flask ; extra == 'flask'
